hiddenbot/__init__.py
hiddenbot/__version__.py
hiddenbot/config.py
hiddenbot/crawl/__init__.py
hiddenbot/crawl/crawler.py
hiddenbot/crawl/extractor.py
hiddenbot/crawl/result.py
hiddenbot/crawl/utils.py
hiddenbot/main.py
hiddenbot/save.py
hiddenbot/tor.py
hiddenbot/urls.py
hiddenbot-0.0.3.dist-info/LICENSE
hiddenbot-0.0.3.dist-info/METADATA
hiddenbot-0.0.3.dist-info/WHEEL
hiddenbot-0.0.3.dist-info/entry_points.txt
hiddenbot-0.0.3.dist-info/RECORD
