Metadata-Version: 2.1
Name: hiddenbot
Version: 0.0.3
Summary: Dark Web Crawler
Author: hdks
Author-email: hdks.bug@gmail.com
Requires-Python: >=3.11,<4.0
Classifier: Programming Language :: Python :: 3
Classifier: Programming Language :: Python :: 3.11
Requires-Dist: beautifulsoup4 (>=4.12.2,<5.0.0)
Requires-Dist: httpx[socks] (>=0.25.0,<0.26.0)
Requires-Dist: stem (>=1.8.2,<2.0.0)
Requires-Dist: tld (>=0.13,<0.14)
Requires-Dist: typer[all] (>=0.9.0,<0.10.0)
Requires-Dist: validators (>=0.22.0,<0.23.0)
